bizdays.py
bizdays-1.0.18.dist-info/METADATA
bizdays-1.0.18.dist-info/WHEEL
bizdays-1.0.18.dist-info/licenses/LICENSE.txt
bizdays-1.0.18.dist-info/RECORD
