Metadata-Version: 2.4
Name: bizdays
Version: 1.0.18
Summary: Functions to handle business days calculations
License-File: LICENSE.txt
Author: wilsonfreitas
Author-email: wilson.freitas@gmail.com
Requires-Python: >=3.9
Classifier: Programming Language :: Python :: 3
Classifier: Programming Language :: Python :: 3.9
Classifier: Programming Language :: Python :: 3.10
Classifier: Programming Language :: Python :: 3.11
Classifier: Programming Language :: Python :: 3.12
Classifier: Programming Language :: Python :: 3.13
Classifier: Programming Language :: Python :: 3.14
Requires-Dist: pandas (>=2,<3)
Requires-Dist: pandas-market-calendars (>=4,<5)
